algoflex/__init__.py
algoflex/__main__.py
algoflex/app.py
algoflex/attempt.py
algoflex/custom_widgets.py
algoflex/dashboard.py
algoflex/db.py
algoflex/home.py
algoflex/questions.py
algoflex/result.py
algoflex/utils.py
algoflex-1.0.2.dist-info/licenses/LICENSE
algoflex-1.0.2.dist-info/METADATA
algoflex-1.0.2.dist-info/WHEEL
algoflex-1.0.2.dist-info/entry_points.txt
algoflex-1.0.2.dist-info/top_level.txt
algoflex-1.0.2.dist-info/RECORD
