Metadata-Version: 2.4
Name: algoflex
Version: 1.0.2
Summary: Algoflex - An algorithm practice TUI
Author-email: ndero <jnderoh@gmail.com>
License-Expression: MIT
Requires-Python: >=3.8
License-File: LICENSE
Requires-Dist: textual>=3.5.0
Requires-Dist: textual[syntax]
Requires-Dist: tinydb>=4.8.2
Dynamic: license-file
